odoo/addons/account_payment_credit_card/README.rst
odoo/addons/account_payment_credit_card/__init__.py
odoo/addons/account_payment_credit_card/__manifest__.py
odoo/addons/account_payment_credit_card/i18n/account_payment_credit_card.pot
odoo/addons/account_payment_credit_card/models/__init__.py
odoo/addons/account_payment_credit_card/models/account.py
odoo/addons/account_payment_credit_card/models/account_move.py
odoo/addons/account_payment_credit_card/readme/CONFIGURE.rst
odoo/addons/account_payment_credit_card/readme/CONTRIBUTORS.rst
odoo/addons/account_payment_credit_card/readme/CREDITS.rst
odoo/addons/account_payment_credit_card/readme/DESCRIPTION.rst
odoo/addons/account_payment_credit_card/readme/INSTALL.rst
odoo/addons/account_payment_credit_card/readme/USAGE.rst
odoo/addons/account_payment_credit_card/static/description/icon.png
odoo/addons/account_payment_credit_card/static/description/index.html
odoo/addons/account_payment_credit_card/views/account_view.xml
odoo11_addon_account_payment_credit_card-11.0.1.0.0.99.dev12.dist-info/METADATA
odoo11_addon_account_payment_credit_card-11.0.1.0.0.99.dev12.dist-info/WHEEL
odoo11_addon_account_payment_credit_card-11.0.1.0.0.99.dev12.dist-info/top_level.txt
odoo11_addon_account_payment_credit_card-11.0.1.0.0.99.dev12.dist-info/RECORD
